pocolog2msgpack/__init__.py
pocolog2msgpack/converter.py
pocolog2msgpack/utilities.py
pocolog2msgpack/x_2_y_file.py
procolog2msgpack/__init__.py
procolog2msgpack/converter.py
procolog2msgpack/utilities.py
procolog2msgpack/x_2_y_file.py
pocolog2msgpack-0.1.2.dist-info/LICENSE
pocolog2msgpack-0.1.2.dist-info/METADATA
pocolog2msgpack-0.1.2.dist-info/WHEEL
pocolog2msgpack-0.1.2.dist-info/top_level.txt
pocolog2msgpack-0.1.2.dist-info/RECORD
