Metadata-Version: 2.1
Name: pocolog2msgpack
Version: 0.1.2
Summary: Python wrapper around procolog2msgpack,
Home-page: UNKNOWN
Author: Johann Hemmann
Author-email: johann.hemmann@dfki.de
License: LGPL-3.0
Project-URL: Source Code, https://github.com/Urhengulas/python-procolog2msgpack
Platform: UNKNOWN
Classifier: License :: OSI Approved :: GNU Lesser General Public License v3 or later (LGPLv3+)
Classifier: Programming Language :: Python :: 3
Classifier: Programming Language :: Python :: 3.5
Classifier: Programming Language :: Python :: 3.6
Classifier: Programming Language :: Python :: 3.7
Requires-Dist: msgpack
Requires-Dist: docker
